Metadata-Version: 2.1
Name: mkdocs-copy
Version: 0.0.1
Summary: A mkdocs plugin that lets you copy (and maybe transform) arbitrary doc files to the build.
Home-page: https://github.com/chikamichi/mkdocs-copy
Author: Jean-Denis Vauguet
Author-email: jd@vauguet.fr
License: MIT
Keywords: mkdocs markdown file copy include export transform
Platform: UNKNOWN
Classifier: Development Status :: 4 - Beta
Classifier: Environment :: Console
Classifier: Environment :: Plugins
Classifier: Intended Audience :: End Users/Desktop
Classifier: Intended Audience :: Developers
Classifier: Intended Audience :: Information Technology
Classifier: Intended Audience :: System Administrators
Classifier: License :: OSI Approved :: MIT License
Classifier: Natural Language :: English
Classifier: Operating System :: OS Independent
Classifier: Programming Language :: Python
Classifier: Programming Language :: Python :: 2.7
Classifier: Programming Language :: Python :: 3
Classifier: Topic :: Documentation
Classifier: Topic :: Text Processing
Classifier: Topic :: Text Processing :: Filters
Classifier: Topic :: Software Development :: Documentation
Classifier: Topic :: Software Development :: Libraries :: Python Modules
Requires-Python: >=2.7
License-File: LICENSE
